CHANGELOG.rst
LICENSE
MANIFEST.in
README.rst
pyproject.toml
setup.cfg
setup.py
tox.ini
Mopidy_NeoPixel.egg-info/PKG-INFO
Mopidy_NeoPixel.egg-info/SOURCES.txt
Mopidy_NeoPixel.egg-info/dependency_links.txt
Mopidy_NeoPixel.egg-info/entry_points.txt
Mopidy_NeoPixel.egg-info/not-zip-safe
Mopidy_NeoPixel.egg-info/requires.txt
Mopidy_NeoPixel.egg-info/top_level.txt
mopidy_neopixel/__init__.py
mopidy_neopixel/ext.conf
mopidy_neopixel/frontend.py
tests/__init__.py
tests/test_extension.py