Metadata-Version: 2.1
Name: Mopidy-NeoPixel
Version: 0.1.1
Summary: You can always add leds to a mopidy player :-)
Home-page: https://github.com/fmatray/mopidy-neopixel
Author: Frédéric Matray-Marin
Author-email: frederic.matray@me.com
License: Apache License, Version 2.0
Download-URL: https://github.com/fmatray/mopidy-neopixel/archive/0.1.1.zip
Keywords: Mopidy,Mopidy-frontend,Neopixels
Platform: UNKNOWN
Classifier: Environment :: No Input/Output (Daemon)
Classifier: Intended Audience :: End Users/Desktop
Classifier: License :: OSI Approved :: Apache Software License
Classifier: Operating System :: OS Independent
Classifier: Programming Language :: Python :: 3
Classifier: Topic :: Multimedia :: Sound/Audio :: Players
Requires-Python: >= 3.7
Provides-Extra: dev
Provides-Extra: lint
Provides-Extra: release
Provides-Extra: test
